add_text/__init__.py
add_text/main.py
add_text/utils.py
background/__init__.py
background/main.py
background/utils.py
concat/__init__.py
concat/main.py
concat/utils.py
cut/__init__.py
cut/main.py
cut/utils.py
download/__init__.py
download/main.py
watermark/__init__.py
watermark/main.py
watermark/utils.py
video_ditor-0.0.3.dist-info/LICENCE.txt
video_ditor-0.0.3.dist-info/METADATA
video_ditor-0.0.3.dist-info/WHEEL
video_ditor-0.0.3.dist-info/entry_points.txt
video_ditor-0.0.3.dist-info/top_level.txt
video_ditor-0.0.3.dist-info/RECORD
