Metadata-Version: 2.1
Name: video-ditor
Version: 0.0.3
Summary: A python package to manipulate videos
Home-page: https://github.com/donwany/video-ditor.git
Author: Theophilus Siameh
Author-email: theodondre@gmail.com
License: MIT License
Keywords: video editor,editor,video manipulator,cut videos,join videos,add watermark to videos
Platform: any
Classifier: Development Status :: 5 - Production/Stable
Classifier: Environment :: Console
Classifier: Intended Audience :: Developers
Classifier: Programming Language :: Python
Classifier: Programming Language :: Python :: 3
Classifier: Programming Language :: Python :: 3 :: Only
Classifier: Programming Language :: Python :: 3.7
Classifier: Programming Language :: Python :: 3.8
Classifier: Programming Language :: Python :: 3.9
Classifier: Programming Language :: Python :: 3.10
Classifier: Programming Language :: Python :: 3.11
Classifier: Programming Language :: Python :: Implementation :: CPython
Classifier: Programming Language :: Python :: Implementation :: PyPy
Classifier: Topic :: Software Development :: Libraries :: Python Modules
Classifier: Topic :: Software Development :: Testing
Classifier: Topic :: Utilities
Requires-Python: >=3.7
Requires-Dist: requests (==2.31.0)
Requires-Dist: loguru (==0.7.0)
Requires-Dist: moviepy (==1.0.3)
Requires-Dist: yt-dlp
